xdr_parser/__init__.py
xdr_parser/data_types/__init__.py
xdr_parser/data_types/base.py
xdr_parser/data_types/constant.py
xdr_parser/data_types/decimal_constant.py
xdr_parser/data_types/declarations/__init__.py
xdr_parser/data_types/declarations/array.py
xdr_parser/data_types/declarations/declaration.py
xdr_parser/data_types/declarations/opaque.py
xdr_parser/data_types/declarations/optional.py
xdr_parser/data_types/declarations/simple.py
xdr_parser/data_types/declarations/string.py
xdr_parser/data_types/declarations/void.py
xdr_parser/data_types/definitions/__init__.py
xdr_parser/data_types/definitions/constant_definition.py
xdr_parser/data_types/definitions/definition.py
xdr_parser/data_types/definitions/enum_definition.py
xdr_parser/data_types/definitions/struct_definition.py
xdr_parser/data_types/definitions/typedef_definition.py
xdr_parser/data_types/definitions/union_definition.py
xdr_parser/data_types/hexadecimal_constant.py
xdr_parser/data_types/identifier.py
xdr_parser/data_types/namespace.py
xdr_parser/data_types/octal_constant.py
xdr_parser/data_types/specifiers/__init__.py
xdr_parser/data_types/specifiers/boolean.py
xdr_parser/data_types/specifiers/double.py
xdr_parser/data_types/specifiers/enum_specifier.py
xdr_parser/data_types/specifiers/float.py
xdr_parser/data_types/specifiers/hyper.py
xdr_parser/data_types/specifiers/identifier_specifier.py
xdr_parser/data_types/specifiers/integer.py
xdr_parser/data_types/specifiers/opaque.py
xdr_parser/data_types/specifiers/quadruple.py
xdr_parser/data_types/specifiers/specifier.py
xdr_parser/data_types/specifiers/struct_specifier.py
xdr_parser/data_types/specifiers/sub/__init__.py
xdr_parser/data_types/specifiers/sub/enum_body.py
xdr_parser/data_types/specifiers/sub/enum_member.py
xdr_parser/data_types/specifiers/sub/struct_body.py
xdr_parser/data_types/specifiers/sub/union_body.py
xdr_parser/data_types/specifiers/sub/union_case.py
xdr_parser/data_types/specifiers/union_specifier.py
xdr_parser-0.0.1.dev0.dist-info/WHEEL
xdr_parser-0.0.1.dev0.dist-info/METADATA
xdr_parser-0.0.1.dev0.dist-info/RECORD
